lmcache/__init__.py
lmcache/_version.py
lmcache/c_ops.cpython-310-x86_64-linux-gnu.so
lmcache/config.py
lmcache/connections.py
lmcache/logging.py
lmcache/native_storage_ops.cpython-310-x86_64-linux-gnu.so
lmcache/non_cuda_equivalents.py
lmcache/observability.py
lmcache/protocol.py
lmcache/usage_context.py
lmcache/utils.py
lmcache/integration/__init__.py
lmcache/integration/sglang/__init__.py
lmcache/integration/sglang/sglang_adapter.py
lmcache/integration/sglang/utils.py
lmcache/integration/vllm/__init__.py
lmcache/integration/vllm/lmcache_connector_v1.py
lmcache/integration/vllm/lmcache_connector_v1_085.py
lmcache/integration/vllm/utils.py
lmcache/integration/vllm/vllm_multi_process_adapter.py
lmcache/integration/vllm/vllm_v1_adapter.py
lmcache/integration/vllm/tests/test_mm_hash_utils.py
lmcache/server/__init__.py
lmcache/server/__main__.py
lmcache/server/server_storage_backend/__init__.py
lmcache/server/server_storage_backend/abstract_backend.py
lmcache/server/server_storage_backend/local_backend.py
lmcache/storage_backend/evictor/__init__.py
lmcache/storage_backend/evictor/base_evictor.py
lmcache/storage_backend/evictor/lru_evictor.py
lmcache/storage_backend/serde/__init__.py
lmcache/storage_backend/serde/cachegen_basics.py
lmcache/storage_backend/serde/cachegen_decoder.py
lmcache/storage_backend/serde/cachegen_encoder.py
lmcache/storage_backend/serde/fast_serde.py
lmcache/storage_backend/serde/safe_serde.py
lmcache/storage_backend/serde/serde.py
lmcache/storage_backend/serde/torch_serde.py
lmcache/tools/controller_benchmark/README.md
lmcache/tools/controller_benchmark/__init__.py
lmcache/tools/controller_benchmark/__main__.py
lmcache/tools/controller_benchmark/benchmark.py
lmcache/tools/controller_benchmark/config.py
lmcache/tools/controller_benchmark/constants.py
lmcache/tools/controller_benchmark/handlers/__init__.py
lmcache/tools/controller_benchmark/handlers/admit.py
lmcache-0.3.13.dist-info/METADATA
lmcache-0.3.13.dist-info/WHEEL
lmcache-0.3.13.dist-info/entry_points.txt
lmcache-0.3.13.dist-info/top_level.txt
lmcache-0.3.13.dist-info/RECORD
lmcache-0.3.13.dist-info/licenses/LICENSE
