Metadata-Version: 2.4
Name: lmcache
Version: 0.3.13
Summary: A LLM serving engine extension to reduce TTFT and increase throughput, especially under long-context scenarios.
Author-email: LMCache Team <lmcacheteam@gmail.com>
License-Expression: Apache-2.0
Project-URL: homepage, https://docs.lmcache.ai
Project-URL: source, https://github.com/LMCache/LMCache
Project-URL: issues, https://github.com/LMCache/LMCache
Classifier: Development Status :: 3 - Alpha
Classifier: Operating System :: POSIX :: Linux
Classifier: Environment :: GPU
Classifier: Programming Language :: Python :: 3.10
Classifier: Programming Language :: Python :: 3.11
Classifier: Programming Language :: Python :: 3.12
Classifier: Programming Language :: Python :: 3.13
Classifier: Programming Language :: Python :: Implementation :: CPython
Classifier: Intended Audience :: Developers
Classifier: Intended Audience :: Information Technology
Classifier: Intended Audience :: Science/Research
Classifier: Topic :: Scientific/Engineering :: Artificial Intelligence
Classifier: Topic :: Scientific/Engineering :: Information Analysis
Requires-Python: <3.14,>=3.10
License-File: LICENSE
Requires-Dist: aiofile
Requires-Dist: aiofiles
Requires-Dist: aiohttp
Requires-Dist: awscrt
Requires-Dist: cufile-python
Requires-Dist: fastapi
Requires-Dist: httpx
Requires-Dist: msgspec
Requires-Dist: nixl; python_version < "3.13"
Requires-Dist: numpy<=2.2.6
Requires-Dist: nvtx
Requires-Dist: prometheus_client>=0.18.0
Requires-Dist: psutil
Requires-Dist: py-cpuinfo
Requires-Dist: pyyaml
Requires-Dist: pyzmq>=25.0.0
Requires-Dist: redis
Requires-Dist: safetensors
Requires-Dist: setuptools<81.0.0,>=77.0.3
Requires-Dist: setuptools_scm>=8
Requires-Dist: sortedcontainers
Requires-Dist: torch
Requires-Dist: transformers>=4.51.1
Requires-Dist: uvicorn
Requires-Dist: httptools
Requires-Dist: cupy-cuda12x
Dynamic: license-file
